Verilog-Indrasen_Gupta_IITKGP/Lecture11-Verilog_Modelling_Examples_(contd.)/Behavioural/add.v
module add(X, Y, Z, sign, carry, parity, zero, overflow);
    input [15:0] X, Y;
    output [15:0] Z;
    output sign, carry, parity, zero, overflow;

    assign {carry, Z} = X + Y;

    assign sign = Z[15];
    assign parity = ~^Z;
    assign zero = ~|Z;
    assign overflow = (X[15] & Y[15] & ~Z[15]) || (~X[15] & ~Y[15] & Z[15]);
endmodule

Verilog-Indrasen_Gupta_IITKGP/Lecture11-Verilog_Modelling_Examples_(contd.)/Behavioural/test.v
`timescale 10ns/1ns

module testbench;
    reg [15:0] X, Y;  // 16-bit inputs for addition
    wire [15:0] Z;    // 16-bit output for sum
    wire carry;       // Carry-out of the addition
    wire sign;        // Sign bit (MSB of result)
    wire parity;      // Parity of the result
    wire zero;        // Zero flag (if result is zero)
    wire overflow;    // Overflow flag

    // Instantiate the add module
    add DUT(
        .X(X),
        .Y(Y),
        .Z(Z),
        .sign(sign),
        .carry(carry),
        .parity(parity),
        .zero(zero),
        .overflow(overflow)
    );

    initial begin
        // Monitor the signals during simulation
        $monitor($time, " X = %h, Y = %h, Z = %h, carry = %b, sign = %b, parity = %b, zero = %b, overflow = %b", 
                 X, Y, Z, carry, sign, parity, zero, overflow);

        // Initialize the waveform dump for GTKWave
        $dumpfile("add.vcd"); //vcd means value change dump
        $dumpvars(0, testbench);
        
        // Test case 1: Simple addition without overflow
        #5 X = 16'h1; Y = 16'h2;
        
        // Test case 2: Addition with carry
        #5 X = 16'hffff; Y = 16'h0001;

        // Test case 3: Overflow case (positive overflow)
        #5 X = 16'h7fff; Y = 16'h0001;

        // Test case 4: Overflow case (negative overflow)
        #5 X = 16'h8000; Y = 16'hffff;

        // Test case 5: Zero result
        #5 X = 16'h0000; Y = 16'h0000;

        // Test case 6: Random values
        #5 X = 16'h3f3f; Y = 16'hc0c0;

        // Test case 7: Parity check
        #5 X = 16'h5555; Y = 16'haaaa;

        // Finish the simulation after all tests
        #5 $finish;
    end
endmodule

Verilog-Indrasen_Gupta_IITKGP/Lecture11-Verilog_Modelling_Examples_(contd.)/Behavioural/add.vcd
$date
	Tue Jan  7 15:21:21 2025
$end
$version
	Icarus Verilog
$end
$timescale
	1ns
$end
$scope module testbench $end
$var wire 1 ! zero $end
$var wire 1 " sign $end
$var wire 1 # parity $end
$var wire 1 $ overflow $end
$var wire 1 % carry $end
$var wire 16 & Z [15:0] $end
$var reg 16 ' X [15:0] $end
$var reg 16 ( Y [15:0] $end
$scope module DUT $end
$var wire 16 ) X [15:0] $end
$var wire 16 * Y [15:0] $end
$var wire 1 $ overflow $end
$var wire 1 ! zero $end
$var wire 1 " sign $end
$var wire 1 # parity $end
$var wire 1 % carry $end
$var wire 16 + Z [15:0] $end
$upscope $end
$upscope $end
$enddefinitions $end
#0
$dumpvars
bx +
bx *
bx )
bx (
bx '
bx &
x%
x$
x#
x"
x!
$end
#50
0$
0"
1#
0!
b11 &
b11 +
0%
b10 (
b10 *
b1 '
b1 )
#100
1!
b0 &
b0 +
1%
b1 (
b1 *
b1111111111111111 '
b1111111111111111 )
#150
1$
1"
0#
0!
b1000000000000000 &
b1000000000000000 +
0%
b111111111111111 '
b111111111111111 )
#200
1$
0"
1%
b111111111111111 &
b111111111111111 +
b1111111111111111 (
b1111111111111111 *
b1000000000000000 '
b1000000000000000 )
#250
0$
1#
1!
b0 &
b0 +
0%
b0 (
b0 *
b0 '
b0 )
#300
0$
1"
0!
b1111111111111111 &
b1111111111111111 +
b1100000011000000 (
b1100000011000000 *
b11111100111111 '
b11111100111111 )
#350
b1010101010101010 (
b1010101010101010 *
b101010101010101 '
b101010101010101 )
