Verilog-Indrasen_Gupta_IITKGP/Lecture11-Verilog_Modelling_Examples_(contd.)/Carry_Look_Ahead_Header/add.v
module add(X, Y, Z, Cin, sign, carry, parity, zero, overflow);
    input [3:0] X, Y;
    input Cin;
    output [3:0] Z;
    output sign, carry, parity, zero, overflow;

    wire p0, p1, p2, p3, g0, g1, g2, g3, c1, c2, c3;

    assign g0 = X[0] & Y[0];
    assign p0 = X[0] ^ Y[0];
    
    assign g1 = X[1] & Y[1];
    assign p1 = X[1] ^ Y[1];

    assign g2 = X[2] & Y[2];
    assign p2 = X[2] ^ Y[2];

    assign g3 = X[3] & Y[3];
    assign p3 = X[3] ^ Y[3];

    assign Z[0] = p0 ^ Cin;

    assign c1 = g0 | (Cin & p0);
    assign Z[1] = p1 ^ c1;

    assign c2 = g1 | (g0 & p1) | (Cin & p0 & p1);
    assign Z[2] = p2 ^ c2;

    assign c3 = g2 | (g1 & p2) | (g0 & p1 & p2) | (Cin & p0 & p1 & p2);
    assign Z[3] = p3 ^ c3;

    assign carry = g3 | (g2 & p3) | (g1 & p2 & p3) | (g0 & p1 & p2 & p3) | (Cin & p0 & p1 & p2 & p3);

    assign sign = Z[3];
    assign parity = ~^Z;
    assign zero = ~|Z;
    assign overflow = (X[3] & Y[3] & ~Z[3]) || (~X[3] & ~Y[3] & Z[3]);

endmodule

Verilog-Indrasen_Gupta_IITKGP/Lecture11-Verilog_Modelling_Examples_(contd.)/Carry_Look_Ahead_Header/test.v
`timescale 10ns/1ns

module testbench;
    reg [3:0] X, Y;  // 4-bit inputs for addition
    reg Cin;         // Carry-in input
    wire [3:0] Z;    // 4-bit output for sum
    wire sign;       // Sign bit (MSB of result)
    wire carry;      // Carry-out of the addition
    wire parity;     // Parity of the result
    wire zero;       // Zero flag (if result is zero)
    wire overflow;   // Overflow flag

    // Instantiate the add module
    add DUT(
        .X(X),
        .Y(Y),
        .Cin(Cin),
        .Z(Z),
        .sign(sign),
        .carry(carry),
        .parity(parity),
        .zero(zero),
        .overflow(overflow)
    );

    initial begin
        // Monitor the signals during simulation
        $monitor($time, " X = %b, Y = %b, Cin = %b, Z = %b, carry = %b, sign = %b, parity = %b, zero = %b, overflow = %b", 
                 X, Y, Cin, Z, carry, sign, parity, zero, overflow);

        // Initialize the waveform dump for GTKWave
        $dumpfile("add.vcd"); //vcd means value change dump
        $dumpvars(0, testbench);
        
        // Test case 1: Simple addition with no carry
        #5 X = 4'b0010; Y = 4'b0011; Cin = 1'b0; // 2 + 3 = 5
        
        // Test case 2: Addition with carry-in
        #5 X = 4'b1111; Y = 4'b0001; Cin = 1'b0; // 15 + 1 = 16 (Carry out)
        
        // Test case 3: Overflow case (positive overflow)
        #5 X = 4'b0111; Y = 4'b0101; Cin = 1'b0; // 7 + 5 = 12 (No overflow)
        
        // Test case 4: Overflow case (negative overflow)
        #5 X = 4'b1000; Y = 4'b1111; Cin = 1'b0; // -8 + -1 = -9 (Overflow)
        
        // Test case 5: Zero result
        #5 X = 4'b0000; Y = 4'b0000; Cin = 1'b0; // 0 + 0 = 0
        
        // Test case 6: Check for parity
        #5 X = 4'b1010; Y = 4'b0101; Cin = 1'b0; // 10 + 5 = 15
        
        // Test case 7: Test for carry-in being 1
        #5 X = 4'b1100; Y = 4'b0011; Cin = 1'b1; // 12 + 3 + 1 (Cin) = 16 (Carry out)
        
        // Test case 8: Random case
        #5 X = 4'b1101; Y = 4'b0110; Cin = 1'b1; // 13 + 6 + 1 (Cin) = 20
        
        // Test case 9: Parity check with all 1's
        #5 X = 4'b1111; Y = 4'b1111; Cin = 1'b0; // 15 + 15 = 30 (Parity check)
        
        // Finish the simulation after all tests
        #5 $finish;
    end
endmodule

Verilog-Indrasen_Gupta_IITKGP/Lecture11-Verilog_Modelling_Examples_(contd.)/Carry_Look_Ahead_Header/add.vcd
$date
	Tue Jan  7 16:04:41 2025
$end
$version
	Icarus Verilog
$end
$timescale
	1ns
$end
$scope module testbench $end
$var wire 1 ! zero $end
$var wire 1 " sign $end
$var wire 1 # parity $end
$var wire 1 $ overflow $end
$var wire 1 % carry $end
$var wire 4 & Z [3:0] $end
$var reg 1 ' Cin $end
$var reg 4 ( X [3:0] $end
$var reg 4 ) Y [3:0] $end
$scope module DUT $end
$var wire 1 ' Cin $end
$var wire 4 * X [3:0] $end
$var wire 4 + Y [3:0] $end
$var wire 1 , c1 $end
$var wire 1 - c2 $end
$var wire 1 . c3 $end
$var wire 1 % carry $end
$var wire 1 / g0 $end
$var wire 1 0 g1 $end
$var wire 1 1 g2 $end
$var wire 1 2 g3 $end
$var wire 1 $ overflow $end
$var wire 1 3 p0 $end
$var wire 1 4 p1 $end
$var wire 1 5 p2 $end
$var wire 1 6 p3 $end
$var wire 1 ! zero $end
$var wire 1 " sign $end
$var wire 1 # parity $end
$var wire 4 7 Z [3:0] $end
$upscope $end
$upscope $end
$enddefinitions $end
#0
$dumpvars
bx 7
x6
x5
x4
x3
x2
x1
x0
x/
x.
x-
x,
bx +
bx *
bx )
bx (
x'
bx &
x%
x$
x#
x"
x!
$end
#50
0$
0"
1#
0%
0.
1-
0!
b101 &
b101 7
0,
0/
13
10
04
01
05
02
06
0'
b11 )
b11 +
b10 (
b10 *
#100
1!
1%
1.
0"
1,
1#
b0 &
b0 7
00
14
1/
03
15
16
b1 )
b1 +
b1111 (
b1111 *
#150
1$
0%
1"
1#
0!
b1100 &
b1100 7
11
05
06
b101 )
b101 +
b111 (
b111 *
#200
0"
0.
1%
0-
1$
0,
0#
b111 &
b111 7
0/
13
01
15
12
b1111 )
b1111 +
b1000 (
b1000 *
#250
0%
0$
1!
1#
b0 &
b0 7
03
04
05
02
b0 )
b0 +
b0 (
b0 *
#300
1"
1#
0!
b1111 &
b1111 7
13
15
14
16
b101 )
b101 +
b1010 (
b1010 *
#350
0"
1!
1%
1.
1-
1,
1#
b0 &
b0 7
1'
b11 )
b11 +
b1100 (
b1100 *
#400
0"
1%
1.
0#
0!
b100 &
b100 7
11
05
b110 )
b110 +
b1101 (
b1101 *
#450
1"
0$
1/
03
12
06
10
04
0#
b1110 &
b1110 7
0'
b1111 )
b1111 +
b1111 (
b1111 *
