Verilog-Indrasen_Gupta_IITKGP/Lecture12-Verilog_Description_Styles/When_a_code_synthesizes_to_mux/mux.v
module generate_mux(data, select, out, f);
    input [15:0] data;   // 16-bit input data
    input [3:0] select;  // 4-bit select signal
    output out;          // Single-bit output for selected data
    output [3:0] f;      // 4-bit output from the conditional operation

    // MUX logic for a 16-bit input using 4-bit select
    assign out = data[select]; // selects the bit corresponding to the select line

    // Conditional operation (f = in[3:0] if sel[0] else in[12:15])
    assign f = select[0] ? data[3:0] : data[7:4]; // Conditional logic for f

endmodule

Verilog-Indrasen_Gupta_IITKGP/Lecture12-Verilog_Description_Styles/When_a_code_synthesizes_to_mux/test.v
module testbench;

    // Inputs to the generate_mux
    reg [15:0] data;   // 16-bit input
    reg [3:0] select;  // 4-bit select signal
    
    // Outputs from the generate_mux
    wire out;          // Single-bit output
    wire [3:0] f;      // 4-bit output

    // Instantiate the generate_mux module
    generate_mux dut (
        .data(data),
        .select(select),
        .out(out),
        .f(f)
    );

    // Initial block for testing the module
    initial begin
        // Display the test results in the console
        $monitor($time, " select=%b, data=%h, out=%b, f=%h", select, data, out, f);

        // Initialize the waveform dump for GTKWave
        $dumpfile("mux.vcd"); //vcd means value change dump
        $dumpvars(0, testbench);

        // Apply test vectors to check different conditions
        #5  data = 16'hA3F1; select = 4'b0000;  // Test select line 0000
        #5  select = 4'b0001;  // Test select line 0001
        #5  select = 4'b0010;  // Test select line 0010
        #5  select = 4'b0100;  // Test select line 0100
        #5  select = 4'b1000;  // Test select line 1000
        #5  select = 4'b1111;  // Test select line 1111

        // Test the conditional part (f)
        #5  data = 16'hA3F1; select = 4'b1001; // Select in[3:0] -> f should be 4'b1111
        #5  select = 4'b0001; // Select in[12:15] -> f should be 4'bA3

        // Finish the simulation after the tests
        #5  $finish;
    end

endmodule

Verilog-Indrasen_Gupta_IITKGP/Lecture12-Verilog_Description_Styles/When_a_code_synthesizes_to_mux/mux.vcd
$date
	Tue Jan  7 18:26:58 2025
$end
$version
	Icarus Verilog
$end
$timescale
	1s
$end
$scope module testbench $end
$var wire 1 ! out $end
$var wire 4 " f [3:0] $end
$var reg 16 # data [15:0] $end
$var reg 4 $ select [3:0] $end
$scope module dut $end
$var wire 16 % data [15:0] $end
$var wire 4 & select [3:0] $end
$var wire 1 ! out $end
$var wire 4 ' f [3:0] $end
$upscope $end
$upscope $end
$enddefinitions $end
#0
$dumpvars
bx '
bx &
bx %
bx $
bx #
bx "
x!
$end
#5
b1111 "
b1111 '
1!
b0 $
b0 &
b1010001111110001 #
b1010001111110001 %
#10
b1 "
b1 '
0!
b1 $
b1 &
#15
b1111 "
b1111 '
b10 $
b10 &
#20
1!
b100 $
b100 &
#25
b1000 $
b1000 &
#30
b1 "
b1 '
b1111 $
b1111 &
#35
b1001 $
b1001 &
#40
0!
b1 $
b1 &
